micro_rag_mcp/__init__.py
micro_rag_mcp/__main__.py
micro_rag_mcp/embedder.py
micro_rag_mcp/index.py
micro_rag_mcp/ingest.py
micro_rag_mcp/server.py
micro_rag_mcp/types.py
micro_rag_mcp/utils.py
micro_rag_mcp-0.1.7.dist-info/METADATA
micro_rag_mcp-0.1.7.dist-info/WHEEL
micro_rag_mcp-0.1.7.dist-info/entry_points.txt
micro_rag_mcp-0.1.7.dist-info/top_level.txt
micro_rag_mcp-0.1.7.dist-info/RECORD
