Metadata-Version: 2.4
Name: micro-rag-mcp
Version: 0.1.7
Summary: Minimal local RAG MCP server for document folders
Requires-Python: >=3.12
Requires-Dist: fastmcp>=1.0.0
Requires-Dist: sentence-transformers>=3.0.0
Requires-Dist: faiss-cpu>=1.8.0
Requires-Dist: numpy>=1.24.0
Requires-Dist: pypdf>=4.0.0
Requires-Dist: python-docx>=1.1.0
Requires-Dist: pydantic>=2.0.0
Requires-Dist: charset-normalizer>=3.0.0
